wink_sdk_ping/__init__.py
wink_sdk_ping/api_client.py
wink_sdk_ping/api_response.py
wink_sdk_ping/configuration.py
wink_sdk_ping/exceptions.py
wink_sdk_ping/py.typed
wink_sdk_ping/rest.py
wink_sdk_ping/api/__init__.py
wink_sdk_ping/api/acl_api.py
wink_sdk_ping/api/ping_api.py
wink_sdk_ping/models/__init__.py
wink_sdk_ping/models/generic_error_message.py
wink_sdk_ping/models/get_hello400_response.py
wink_sdk_ping/models/ping400_response.py
wink_sdk_ping-0.0.57.dist-info/licenses/LICENSE
wink_sdk_ping-0.0.57.dist-info/METADATA
wink_sdk_ping-0.0.57.dist-info/WHEEL
wink_sdk_ping-0.0.57.dist-info/top_level.txt
wink_sdk_ping-0.0.57.dist-info/RECORD
